{
  "name": "BuzzAdBenefit",
  "platforms": {
    "ios": "10.0"
  },
  "requires_arc": true,
  "summary": "BuzzAdBenefit library for core functions related to serving advertisements.",
  "description": "BuzzAdBenefit library for core functions related to serving advertisements. The BuzzAd Benefit SDK makes it easy to serve advertisements with benefit in your iOS app.",
  "version": "3.0.0",
  "license": {
    "type": "MIT",
    "file": "LICENSE"
  },
  "authors": "Buzzvil",
  "homepage": "https://www.buzzvil.com",
  "source": {
    "http": "https://storage.googleapis.com/buzzvil-client-app/bab-ios/893/BuzzAdBenefit.zip"
  },
  "vendored_frameworks": [
    "BuzzAdBenefit.framework"
  ],
  "dependencies": {
    "BuzzConfig": [
      "~> 0.1.0"
    ],
    "BuzzServiceApi": [
      "~> 0.1.0"
    ],
    "BuzzAd": [
      "~> 0.1.0"
    ],
    "BuzzUnit": [
      "~> 0.1.0"
    ],
    "AFNetworking": [
      "~> 4.0"
    ],
    "ReactiveObjC": [
      "~> 3.1.1"
    ],
    "BuzzBaseReward": [
      "~> 0.1.0"
    ],
    "BuzzInsight": [
      "~> 0.0.2"
    ],
    "BuzzResource": [
      "~> 0.1.0"
    ]
  },
  "pod_target_xcconfig": {
    "EXCLUDED_ARCHS[sdk=iphonesimulator*]": "arm64"
  },
  "user_target_xcconfig": {
    "EXCLUDED_ARCHS[sdk=iphonesimulator*]": "arm64"
  }
}
